minflow/AFLOWpi_ACBN0.py
minflow/QEcalculator.py
minflow/QEpp.py
minflow/QEscript.py
minflow/__init__.py
minflow/cluster_sets.py
minflow/special_functions.py
minflow/banduppy/__init__.py
minflow/banduppy/unfolding_path.py
minflow/banduppyorig/__init__.py
minflow/banduppyorig/oldunfolding_path.py
minflow/banduppyorig/unfolding_path.py
minflow/kgrid/__init__.py
minflow/kgrid/cli.py
minflow/kgrid/series.py
minflow-0.0.1.dist-info/METADATA
minflow-0.0.1.dist-info/WHEEL
minflow-0.0.1.dist-info/top_level.txt
minflow-0.0.1.dist-info/RECORD
