Metadata-Version: 2.1
Name: minflow
Version: 0.0.1
Summary: A basic package for a customized workflow using quantum espresso or abinit.
Author: Rogerio Gouvea
Author-email: <rogeriog.em@gmail.com>
License: UNKNOWN
Keywords: python,dft,workflow,quantumespresso,abinit
Platform: UNKNOWN
Classifier: Programming Language :: Python :: 3
Classifier: Operating System :: Unix
Requires-Dist: AFLOWpi (==1.3.1)
Requires-Dist: ase (==3.22.1)
Requires-Dist: cycler (==0.11.0)
Requires-Dist: irrep (==1.8.1)
Requires-Dist: matplotlib (==3.5.1)
Requires-Dist: numpy (==1.23.5)
Requires-Dist: pandas (==1.4.2)
Requires-Dist: scipy (==1.7.3)
Requires-Dist: setuptools (==61.2.0)
